lazar/__init__.py
lazar/core/array.py
lazar/core/math.py
lazar/nl/__init__.py
lazar/nl/models.py
lazar/nl/tokenizer.py
lazar/utils/__init__.py
lazar/utils/benchmark.py
lazar/utils/ops.py
lazar-1.0.2.dist-info/METADATA
lazar-1.0.2.dist-info/WHEEL
lazar-1.0.2.dist-info/top_level.txt
lazar-1.0.2.dist-info/RECORD
