Metadata-Version: 2.4
Name: lazar
Version: 1.0.2
Summary: A lightweight but powerful alternative to NumPy and Transformers
Home-page: https://github.com/Eternals-Satya/lazar
Author: xycan
Author-email: xycan <eternals.tolong@gmail.com>
Project-URL: Homepage, https://github.com/Eternals-Satya/lazar
Project-URL: Documentation, https://github.com/Eternals-Satya/lazar#readme
Classifier: Programming Language :: Python :: 3
Classifier: License :: OSI Approved :: MIT License
Classifier: Operating System :: OS Independent
Requires-Python: >=3.7
Dynamic: author
Dynamic: home-page
Dynamic: requires-python
